meshagent/livekit/__init__.py
meshagent/livekit/livekit_protocol.py
meshagent/livekit/livekit_protocol_test.py
meshagent/livekit/version.py
meshagent/livekit/agents/meeting_transcriber.py
meshagent/livekit/agents/transcriber.py
meshagent/livekit/agents/transcript_logger.py
meshagent/livekit/agents/voice.py
meshagent_livekit-0.25.1.dist-info/licenses/LICENSE
meshagent_livekit-0.25.1.dist-info/METADATA
meshagent_livekit-0.25.1.dist-info/WHEEL
meshagent_livekit-0.25.1.dist-info/top_level.txt
meshagent_livekit-0.25.1.dist-info/RECORD
