Metadata-Version: 2.4
Name: meshagent-livekit
Version: 0.25.1
Summary: Livekit support for Meshagent
License-Expression: Apache-2.0
Project-URL: Documentation, https://docs.meshagent.com
Project-URL: Website, https://www.meshagent.com
Project-URL: Source, https://www.meshagent.com
Requires-Python: >=3.13
License-File: LICENSE
Requires-Dist: pytest~=8.4
Requires-Dist: pytest-asyncio~=0.26
Requires-Dist: strip-markdown~=1.3
Requires-Dist: livekit==1.0.20
Requires-Dist: livekit-api~=1.1
Requires-Dist: livekit-agents~=1.3
Requires-Dist: livekit-plugins-openai~=1.3
Requires-Dist: livekit-plugins-silero~=1.3
Requires-Dist: livekit-plugins-turn-detector~=1.3
Requires-Dist: meshagent-api~=0.25.1
Requires-Dist: meshagent-tools~=0.25.1
Dynamic: license-file
